dmind
