Metadata-Version: 2.1
Name: dmind
Version: 0.0.5
Summary: a mindmap tool for jupyter notebook
Home-page: https://github.com/dust8/dmind
Author: dust8
License: UNKNOWN
Keywords: dmind mind mindmap
Platform: UNKNOWN
Classifier: Development Status :: 5 - Production/Stable
Classifier: Intended Audience :: Developers
Classifier: Programming Language :: Python :: 2.7
Classifier: Programming Language :: Python :: 3
Classifier: Programming Language :: Python :: 3.4
Classifier: Programming Language :: Python :: 3.5
Classifier: Programming Language :: Python :: 3.6
Classifier: Programming Language :: Python :: 3.7
Classifier: Framework :: IPython
